dj_core/__init__.py
dj_core/apps.py
dj_core/celery.py
dj_core/config.py
dj_core/settings.py
dj_core/skeleton_data.py
dj_core/storage.py
dj_core/urls.py
dj_core/utils.py
dj_core/wsgi.py
dj_core/management/__init__.py
dj_core/management/commands/__init__.py
dj_core/management/commands/setup_skeletons.py
dj_core-0.2.0.dist-info/METADATA
dj_core-0.2.0.dist-info/RECORD
dj_core-0.2.0.dist-info/WHEEL
dj_core-0.2.0.dist-info/top_level.txt
