Metadata-Version: 2.1
Name: dj-core
Version: 0.2.0
Summary: A self-contained and extensible Django environment
Home-page: https://github.com/ionata/dj-core
Author: Ionata Digital
Author-email: webmaster@ionata.com.au
License: BSD 3-Clause License
Platform: UNKNOWN
Classifier: Environment :: Web Environment
Classifier: Framework :: Django
Classifier: Intended Audience :: Developers
Classifier: License :: OSI Approved :: BSD License
Classifier: Operating System :: OS Independent
Classifier: Programming Language :: Python
Classifier: Programming Language :: Python :: 3
Classifier: Programming Language :: Python :: 3.5
Classifier: Programming Language :: Python :: 3.6
Requires-Python: >=3.5
Provides-Extra: defaults
Requires-Dist: django (>=1.11.0)
Requires-Dist: django-environ (>=0.4.0)
Provides-Extra: defaults
Requires-Dist: boto3 (>=1.5.0); extra == 'defaults'
Requires-Dist: celery[redis] (>=4.1.0); extra == 'defaults'
Requires-Dist: django-anymail[mailgun] (>=2.0); extra == 'defaults'
Requires-Dist: django-cors-headers (>=2.2.0); extra == 'defaults'
Requires-Dist: django-debug-toolbar (>=1.9.1); extra == 'defaults'
Requires-Dist: django-extensions (>=2.0.6); extra == 'defaults'
Requires-Dist: django-minimal-user (>=0.0.2); extra == 'defaults'
Requires-Dist: django-storages (>=1.6.6); extra == 'defaults'
Requires-Dist: psycopg2 (>=2.0.0); extra == 'defaults'
